{
  "mockup_url": "https://sandybrown-nightingale-600381.hostingersite.com/2026/05/15/spec16-p7-mockup-baseline-2026-05-15/",
  "sgs_url": "https://sandybrown-nightingale-600381.hostingersite.com/2026/05/15/spec16-p7-converter-v2-output-2026-05-15/",
  "viewport": "375x812",
  "mockup_dimensions": [
    343,
    1112
  ],
  "sgs_dimensions": [
    343,
    1070
  ],
  "aligned_dimensions": [
    343,
    880
  ],
  "mismatched_pixels": 107674,
  "total_pixels": 301840,
  "mismatch_percent": 35.6725,
  "threshold_percent": 1.0,
  "verdict": "FAIL",
  "captured_at": "2026-05-16T04:51:11.452882+00:00"
}